{
  ".": "0.2.0",
  "apps/api": "0.2.0",
  "apps/web": "0.2.0",
  "apps/desktop": "0.2.0",
  "packages/application-client": "0.2.0",
  "packages/application-server": "0.2.0",
  "packages/contracts": "0.2.0",
  "packages/domain-client": "0.2.0",
  "packages/domain-server": "0.2.0",
  "packages/infrastructure-client": "0.2.0",
  "packages/infrastructure-server": "0.2.0",
  "packages/ui-core": "0.2.0",
  "packages/ui-react": "0.2.0",
  "packages/ui-shadcn": "0.2.0",
  "packages/ui-vue": "0.2.0",
  "packages/ui-vuetify": "0.2.0",
  "packages/utils": "0.2.0",
  "packages/test-utils": "0.2.0",
  "packages/assets": "0.2.0",
  "packages/sync-client": "0.2.0"
}
